afipcaeqrdecode/__init__.py
afipcaeqrdecode/convert_first_page_of_pdf_to_image.py
afipcaeqrdecode/decode_cae_url.py
afipcaeqrdecode/extract_images_from_invoice_pdf.py
afipcaeqrdecode/get_cae_metadata.py
afipcaeqrdecode-0.0.14.dist-info/METADATA
afipcaeqrdecode-0.0.14.dist-info/WHEEL
afipcaeqrdecode-0.0.14.dist-info/top_level.txt
afipcaeqrdecode-0.0.14.dist-info/RECORD
