Metadata-Version: 2.1
Name: afipcaeqrdecode
Version: 0.0.14
Summary: Package to decode and extract invoice metadata from an AFIP CAE qr code link
Home-page: https://github.com/mezka/afipcaeqrdecode
Author: Emiliano Mesquita
License: LGPLv3
Platform: UNKNOWN
Requires-Dist: PyJWT (==2.8.0)
Requires-Dist: PyMuPDF (==1.23.7)
Requires-Dist: PyMuPDFb (==1.23.7)
Requires-Dist: json-repair (==0.8.0)
Requires-Dist: numpy (==1.26.2)
Requires-Dist: opencv-python (==4.8.1.78)
Requires-Dist: pdf2image (==1.16.3)
Requires-Dist: qreader (==3.12)
